README.rst
ascribe.py
setup.cfg
setup.py
ascribe.egg-info/PKG-INFO
ascribe.egg-info/SOURCES.txt
ascribe.egg-info/dependency_links.txt
ascribe.egg-info/pbr.json
ascribe.egg-info/requires.txt
ascribe.egg-info/top_level.txt