Metadata-Version: 1.1
Name: ascribe
Version: 0.0.8.dev1
Summary: ascribe api
Home-page: https://ascribe.readthedocs.org
Author: Oskar Paolini, Sylvain Bellemare
Author-email: sylvain@ascribe.io
License: MIT
Keywords: intellectual property,attribution,ownership,art,blockchain,api digital work,provenance,spool
Platform: UNKNOWN
Classifier: Development Status :: 3 - Alpha
Classifier: Intended Audience :: Developers
Classifier: License :: OSI Approved :: MIT License
Classifier: Programming Language :: Python :: 2.7
Classifier: Programming Language :: Python :: 3
Classifier: Programming Language :: Python :: 3.3
Classifier: Programming Language :: Python :: 3.4
Classifier: Programming Language :: Python :: 3.5
